{
  "preRequisites:9": {
    "0:10": {
      "questIDHigh:4": 721792922882491367,
      "questIDLow:4": -7723579044152983038
    },
    "1:10": {
      "questIDHigh:4": 0,
      "questIDLow:4": 99
    }
  },
  "properties:10": {
    "betterquesting:10": {
      "autoClaim:1": 0,
      "desc:8": "You will need some medium voltage cables so lets make some.  There are several available MV Cables.  The best are Copper and Annealed Copper.  Annealed Copper is just a higher temperature copper and both use 1 amp per 1x cable and 1 EU/block loss.  Constantan is also available as it can carry 3 amps per 2x cable but has a 3EU/block loss.  For this quest it just makes sense to use regular copper cables.\n§a\nTo complete the quest craft:\n4 4x Copper Cables -OR-\n2 8x Copper Cables",
      "globalShare:1": 0,
      "icon:10": {
        "Count:3": 1,
        "Damage:2": 28373,
        "OreDict:8": "",
        "id:8": "gregtech:gt.multitileentity"
      },
      "isMain:1": 0,
      "isSilent:1": 0,
      "lockedProgress:1": 0,
      "name:8": "Medium Voltage (MV) Cables",
      "questLogic:8": "AND",
      "repeatTime:3": -1,
      "repeat_relative:1": 1,
      "simultaneous:1": 0,
      "snd_complete:8": "random.levelup",
      "snd_update:8": "random.levelup",
      "taskLogic:8": "OR",
      "visibility:8": "ALWAYS"
    }
  },
  "questIDHigh:4": 3318498257319184290,
  "questIDLow:4": -7642105273181172061,
  "rewards:9": {
    "0:10": {
      "choices:9": {
        "0:10": {
          "Count:3": 1,
          "Damage:2": 2005,
          "OreDict:8": "",
          "id:8": "gregtech:gt.multiitem.food"
        },
        "1:10": {
          "Count:3": 1,
          "Damage:2": 2003,
          "OreDict:8": "",
          "id:8": "gregtech:gt.multiitem.food"
        }
      },
      "ignoreDisabled:1": 0,
      "index:3": 0,
      "rewardID:8": "bq_standard:choice"
    }
  },
  "tasks:9": {
    "0:10": {
      "autoConsume:1": 0,
      "consume:1": 0,
      "groupDetect:1": 0,
      "ignoreNBT:1": 1,
      "index:3": 0,
      "partialMatch:1": 1,
      "requiredItems:9": {
        "0:10": {
          "Count:3": 2,
          "Damage:2": 28369,
          "OreDict:8": "",
          "id:8": "gregtech:gt.multitileentity"
        }
      },
      "taskID:8": "bq_standard:retrieval"
    },
    "1:10": {
      "autoConsume:1": 0,
      "consume:1": 0,
      "groupDetect:1": 0,
      "ignoreNBT:1": 1,
      "index:3": 1,
      "partialMatch:1": 1,
      "requiredItems:9": {
        "0:10": {
          "Count:3": 1,
          "Damage:2": 28373,
          "OreDict:8": "",
          "id:8": "gregtech:gt.multitileentity"
        }
      },
      "taskID:8": "bq_standard:retrieval"
    }
  }
}